{
    "block-rock-rhyolite": "Roche de rhyolite",
    "block-rock-dolostone": "Roche de dolomie",
    "block-rock-siltstone": "Roche de siltite",
    "block-rock-quartzite": "Roche de quartzite",
    "block-rock-gneiss": "Roche de gneiss",
    "block-rock-schist": "Roche schisteuse",
    "block-rock-migmatite": "Roche migmatite",
    "block-rock-amphibolite": "Roche amphibolite",
    "block-rock-pumice": "Roche de pierre ponce",
    "block-rock-diorite": "Roche de diorite",
    "block-rock-gabbro": "Roche de gabbro",
    "block-rock-mudstone": "Roche de argilite",
    "game:block-rock-jade": "Roche de jade",
    "game:block-rock-jasper": "Roche de jaspe",

    "block-cobblestonefan-rhyolite-*": "Pavé de rhyolite en éventail",
    "block-cobblestonefan-dolostone-*": "Pavé de dolomie en éventail",
    "block-cobblestonefan-siltstone-*": "Pavé de siltite en éventail",
    "block-cobblestonefan-quartzite-*": "Pavé de quartzite en éventail",
    "block-cobblestonefan-gneiss-*": "Pavé de gneiss en éventail",
    "block-cobblestonefan-schist-*": "Pavé schisteux en éventail",
    "block-cobblestonefan-migmatite-*": "Pavé de migmatite en éventail",
    "block-cobblestonefan-amphibolite-*": "Pavé d'amphibolite en éventail",
    "block-cobblestonefan-pumice-*": "Pavé de pierre ponce en éventail",
    "block-cobblestonefan-diorite-*": "Pavé de diorite en éventail",
    "block-cobblestonefan-gabbro-*": "Pavé de gabbro en éventail",
    "block-cobblestonefan-mudstone-*": "Pavé de argilite en éventail",
    "game:block-cobblestonefan-jade-*": "Pavé de jade en éventail",
    "game:block-cobblestonefan-jasper-*": "Pavé de jaspe en éventail",

    "block-crackedrock-rhyolite": "Roche de rhyolite fissurée",
    "block-crackedrock-dolostone": "Roche de dolomie fissurée",
    "block-crackedrock-siltstone": "Roche de siltite fissurée",
    "block-crackedrock-quartzite": "Roche de quartzite fissurée",
    "block-crackedrock-gneiss": "Roche de gneiss fissurée",
    "block-crackedrock-schist": "Roche schisteuse fissurée",
    "block-crackedrock-migmatite": "Roche de migmatite fissurée",
    "block-crackedrock-amphibolite": "Roche d'amphibolite fissurée",
    "block-crackedrock-pumice": "Roche de pierre ponce fissurée",
    "block-crackedrock-diorite": "Roche de diorite fissurée",
    "block-crackedrock-gabbro": "Roche de gabbro fissurée",
    "block-crackedrock-mudstone": "Roche de argilite fissurée",
    "game:block-crackedrock-jade": "Roche de jade fissurée",
    "game:block-crackedrock-jasper": "Roche de jaspe fissurée",

    "block-drystonefence-rhyolite-ew-free": "Clôture en pierre sèche de rhyolite",
    "block-drystonefence-dolostone-ew-free": "Clôture en pierre sèche de dolomie",
    "block-drystonefence-siltstone-ew-free": "Clôture en pierre sèche de siltite",
    "block-drystonefence-quartzite-ew-free": "Clôture en pierre sèche de quartzite",
    "block-drystonefence-gneiss-ew-free": "Clôture en pierre sèche de gneiss",
    "block-drystonefence-schist-ew-free": "Clôture en pierre sèche de schiste",
    "block-drystonefence-migmatite-ew-free": "Clôture en pierre sèche de migmatite",
    "block-drystonefence-amphibolite-ew-free": "Clôture en pierre sèche d'amphibolite",
    "block-drystonefence-pumice-ew-free": "Clôture en pierre sèche de pierre ponce",
    "block-drystonefence-diorite-ew-free": "Clôture en pierre sèche de diorite",
    "block-drystonefence-gabbro-ew-free": "Clôture en pierre sèche de gabbro",
    "block-drystonefence-mudstone-ew-free": "Clôture en pierre sèche de argilite",
    "block-drystonefence-jade-ew-free": "Clôture en pierre sèche de jade",
    "block-drystonefence-jasper-ew-free": "Clôture en pierre sèche de jaspe",

    "block-cobbleskull-rhyolite": "Crâne de pavé de rhyolite",
    "block-cobbleskull-dolostone": "Crâne de pavé de dolomie",
    "block-cobbleskull-siltstone": "Crâne de pavé de siltite",
    "block-cobbleskull-quartzite": "Crâne de pavé de quartzite",
    "block-cobbleskull-gneiss": "Crâne de pavé de gneiss",
    "block-cobbleskull-schist": "Crâne de pavé schisteux",
    "block-cobbleskull-migmatite": "Crâne de pavé de migmatite",
    "block-cobbleskull-amphibolite": "Crâne de pavé d'amphibolite",
    "block-cobbleskull-pumice": "Crâne de pavé de pierre ponce",
    "block-cobbleskull-diorite": "Crâne de pavé de diorite",
    "block-cobbleskull-gabbro": "Crâne de pavé de gabbro",
    "block-cobbleskull-mudstone": "Crâne de pavé de argilite",
    "block-cobbleskull-jade": "Crâne de pavé de jade",
    "block-cobbleskull-jasper": "Crâne de pavé de jaspe",

    "block-drystone-rhyolite": "Pierre sèche de rhyolite",
    "block-drystone-dolostone": "Pierre sèche de dolomie",
    "block-drystone-siltstone": "Pierre sèche de siltite",
    "block-drystone-quartzite": "Pierre sèche de quartzite",
    "block-drystone-gneiss": "Pierre sèche de gneiss",
    "block-drystone-schist": "Pierre sèche de schiste",
    "block-drystone-migmatite": "Pierre sèche de migmatite",
    "block-drystone-amphibolite": "Pierre sèche d'amphibolite",
    "block-drystone-pumice": "Pierre sèche de pierre ponce",
    "block-drystone-diorite": "Pierre sèche de diorite",
    "block-drystone-gabbro": "Pierre sèche de gabbro",
    "block-drystone-mudstone": "Pierre sèche de argilite",
    "block-drystone-jade": "Pierre sèche de jade",
    "block-drystone-jasper": "Pierre sèche de jaspe",

    "block-rockpolished-rhyolite": "Roche de rhyolite (Polie)",
    "block-rockpolished-dolostone": "Roche de dolomie (Polie)",
    "block-rockpolished-siltstone": "Roche de siltite (Polie)",
    "block-rockpolished-quartzite": "Roche de quartzite (Polie)",
    "block-rockpolished-gneiss": "Roche de gneiss (Polie)",
    "block-rockpolished-schist": "Roche de schiste (Polie)",
    "block-rockpolished-migmatite": "Roche de migmatite (Polie)",
    "block-rockpolished-amphibolite": "Roche d'amphibolite (Polie)",
    "block-rockpolished-pumice": "Roche de pierre ponce (Polie)",
    "block-rockpolished-diorite": "Roche de diorite (Polie)",
    "block-rockpolished-gabbro": "Roche de gabbro (Polie)",
    "block-rockpolished-mudstone": "Roche de argilite (Polie)",
    "block-rockpolished-jade": "Roche de jade (Polie)",
    "block-rockpolished-jasper": "Roche de jaspe (Polie)",

    "block-stonebricks-rhyolite": "Briques de rhyolite",
    "block-stonebricks-dolostone": "Briques de dolomie",
    "block-stonebricks-siltstone": "Briques de siltite",
    "block-stonebricks-quartzite": "Briques de quartzite",
    "block-stonebricks-gneiss": "Briques de gneiss",
    "block-stonebricks-schist": "Briques de schiste",
    "block-stonebricks-migmatite": "Briques de migmatite",
    "block-stonebricks-amphibolite": "Briques d'amphibolite",
    "block-stonebricks-pumice": "Briques de pierre ponce",
    "block-stonebricks-diorite": "Briques de diorite",
    "block-stonebricks-gabbro": "Briques de gabbro",
    "block-stonebricks-mudstone": "Briques de argilite",
    "block-stonebricks-jasper": "Briques de jaspe",
    "block-stonebricks-jade": "Briques de jade",

    "block-cobblestone-rhyolite": "Pavé de rhyolite",
    "block-cobblestone-dolostone": "Pavé de dolomie",
    "block-cobblestone-siltstone": "Pavé de siltite",
    "block-cobblestone-quartzite": "Pavé de quartzite",
    "block-cobblestone-gneiss": "Pavé de gneiss",
    "block-cobblestone-schist": "Pavé schisteux",
    "block-cobblestone-migmatite": "Pavé de migmatite",
    "block-cobblestone-amphibolite": "Pavé d'amphibolite",
    "block-cobblestone-pumice": "Pavé de pierre ponce",
    "block-cobblestone-diorite": "Pavé de diorite",
    "block-cobblestone-gabbro": "Pavé de gabbro",
    "block-cobblestone-mudstone": "Pavé de argilite",
    "block-cobblestone-jade": "Pavé de jade",
    "block-cobblestone-jasper": "Pavé de jaspe",

    "block-cobblestonestairs-rhyolite-up-north-free": "Escaliers en pavé de rhyolite",
    "block-cobblestonestairs-dolostone-up-north-free": "Escaliers en pavé de dolomie",
    "block-cobblestonestairs-siltstone-up-north-free": "Escaliers en pavé de siltite",
    "block-cobblestonestairs-quartzite-up-north-free": "Escaliers en pavé de quartzite",
    "block-cobblestonestairs-gneiss-up-north-free": "Escaliers en pavé de gneiss",
    "block-cobblestonestairs-schist-up-north-free": "Escaliers en pavé schisteux",
    "block-cobblestonestairs-migmatite-up-north-free": "Escaliers en pavé de migmatite",
    "block-cobblestonestairs-amphibolite-up-north-free": "Escaliers en pavé d'amphibolite",
    "block-cobblestonestairs-pumice-up-north-free": "Escaliers en pavé de pierre ponce",
    "block-cobblestonestairs-diorite-up-north-free": "Escaliers en pavé de diorite",
    "block-cobblestonestairs-gabbro-up-north-free": "Escaliers en pavé de gabbro",
    "block-cobblestonestairs-mudstone-up-north-free": "Escaliers en pavé de argilite",
    "block-cobblestonestairs-jade-up-north-free": "Escaliers en pavé de jade",
    "block-cobblestonestairs-jasper-up-north-free": "Escaliers en pavé de jaspe",

    "block-cobblestoneslab-rhyolite-down-free": "Dalle de pavés en rhyolite",
    "block-cobblestoneslab-dolostone-down-free": "Dalle de pavés en dolomite",
    "block-cobblestoneslab-siltstone-down-free": "Dalle de pavés en siltite",
    "block-cobblestoneslab-quartzite-down-free": "Dalle de pavés en quartzite",
    "block-cobblestoneslab-gneiss-down-free": "Dalle de pavés en gneiss",
    "block-cobblestoneslab-schist-down-free": "Dalle de pavés en schiste",
    "block-cobblestoneslab-migmatite-down-free": "Dalle de pavés en migmatite",
    "block-cobblestoneslab-amphibolite-down-free": "Dalle de pavés en amphibolite",
    "block-cobblestoneslab-pumice-down-free": "Dalle de pavés en pumice",
    "block-cobblestoneslab-diorite-down-free": "Dalle de pavés en diorite",
    "block-cobblestoneslab-gabbro-down-free": "Dalle de pavés en gabbro",
    "block-cobblestoneslab-mudstone-down-free": "Dalle de pavés en argilite",
    "block-cobblestoneslab-jade-down-free": "Dalle de pavés en jade",
    "block-cobblestoneslab-jasper-down-free": "Dalle de pavés en jaspe",

    "block-stonebrickstairs-rhyolite-up-north-free": "Escaliers en briques de pierre en rhyolite",
    "block-stonebrickstairs-dolostone-up-north-free": "Escaliers en briques de pierre en dolomite",
    "block-stonebrickstairs-siltstone-up-north-free": "Escaliers en briques de pierre en siltite",
    "block-stonebrickstairs-quartzite-up-north-free": "Escaliers en briques de pierre en quartzite",
    "block-stonebrickstairs-gneiss-up-north-free": "Escaliers en briques de pierre en gneiss",
    "block-stonebrickstairs-schist-up-north-free": "Escaliers en briques de pierre en schiste",
    "block-stonebrickstairs-migmatite-up-north-free": "Escaliers en briques de pierre en migmatite",
    "block-stonebrickstairs-amphibolite-up-north-free": "Escaliers en briques de pierre en amphibolite",
    "block-stonebrickstairs-pumice-up-north-free": "Escaliers en briques de pierre en pumice",
    "block-stonebrickstairs-diorite-up-north-free": "Escaliers en briques de pierre en diorite",
    "block-stonebrickstairs-gabbro-up-north-free": "Escaliers en briques de pierre en gabbro",
    "block-stonebrickstairs-mudstone-up-north-free": "Escaliers en briques de pierre en argilite",
    "block-stonebrickstairs-jade-up-north-free": "Escaliers en briques de pierre en jade",
    "block-stonebrickstairs-jasper-up-north-free": "Escaliers en briques de pierre en jaspe",

    "block-stonebrickslab-rhyolite-down-free": "Dalle de briques de pierre en rhyolite",
    "block-stonebrickslab-dolostone-down-free": "Dalle de briques de pierre en dolomite",
    "block-stonebrickslab-siltstone-down-free": "Dalle de briques de pierre en siltite",
    "block-stonebrickslab-quartzite-down-free": "Dalle de briques de pierre en quartzite",
    "block-stonebrickslab-gneiss-down-free": "Dalle de briques de pierre en gneiss",
    "block-stonebrickslab-schist-down-free": "Dalle de briques de pierre en schiste",
    "block-stonebrickslab-migmatite-down-free": "Dalle de briques de pierre en migmatite",
    "block-stonebrickslab-amphibolite-down-free": "Dalle de briques de pierre en amphibolite",
    "block-stonebrickslab-pumice-down-free": "Dalle de briques de pierre en pumice",
    "block-stonebrickslab-diorite-down-free": "Dalle de briques de pierre en diorite",
    "block-stonebrickslab-gabbro-down-free": "Dalle de briques de pierre en gabbro",
    "block-stonebrickslab-mudstone-down-free": "Dalle de briques de pierre en argilite",
    "block-stonebrickslab-jasper-down-free": "Dalle de briques de pierre en jaspe",
    "block-stonebrickslab-jade-down-free": "Dalle de briques de pierre en jade",


    "block-polishedrockslab-rhyolite-down-free": "Dalle de roche en rhyolite (Polie)",
    "block-polishedrockslab-dolostone-down-free": "Dalle de roche en dolomite (Polie)",
    "block-polishedrockslab-siltstone-down-free": "Dalle de roche en siltite (Polie)",
    "block-polishedrockslab-quartzite-down-free": "Dalle de roche en quartzite (Polie)",
    "block-polishedrockslab-gneiss-down-free": "Dalle de roche en gneiss (Polie)",
    "block-polishedrockslab-schist-down-free": "Dalle de roche en schiste (Polie)",
    "block-polishedrockslab-migmatite-down-free": "Dalle de roche en migmatite (Polie)",
    "block-polishedrockslab-amphibolite-down-free": "Dalle de roche en amphibolite (Polie)",
    "block-polishedrockslab-pumice-down-free": "Dalle de roche en pumice (Polie)",
    "block-polishedrockslab-diorite-down-free": "Dalle de roche en diorite (Polie)",
    "block-polishedrockslab-gabbro-down-free": "Dalle de roche en gabbro (Polie)",
    "block-polishedrockslab-mudstone-down-free": "Dalle de roche en argilite (Polie)",
    "block-polishedrockslab-jade-down-free": "Dalle de roche en jade (Polie)",
    "block-polishedrockslab-jasper-down-free": "Dalle de roche en jaspe (Polie)",
        
    "block-looseboulders-rhyolite-free": "Rochers en rhyolite",
    "block-looseboulders-dolostone-free": "Rochers en dolomite",
    "block-looseboulders-siltstone-free": "Rochers en siltite",
    "block-looseboulders-quartzite-free": "Rochers en quartzite",
    "block-looseboulders-gneiss-free": "Rochers en gneiss",
    "block-looseboulders-schist-free": "Rochers en schiste",
    "block-looseboulders-migmatite-free": "Rochers en migmatite",
    "block-looseboulders-amphibolite-free": "Rochers en amphibolite",
    "block-looseboulders-pumice-free": "Rochers en pumice",
    "block-looseboulders-diorite-free": "Rochers en diorite",
    "block-looseboulders-gabbro-free": "Rochers en gabbro",
    "block-looseboulders-mudstone-free": "Rochers en argilite",
    "block-looseboulders-jade-free": "Rochers en jade",
    "block-looseboulders-jasper-free": "Rochers en jaspe",

    "block-loosestones-rhyolite-free": "Pierre de rhyolite",
    "block-loosestones-dolostone-free": "Pierre de dolostone",
    "block-loosestones-siltstone-free": "Pierre de siltite",
    "block-loosestones-quartzite-free": "Pierre de quartzite",
    "block-loosestones-gneiss-free": "Pierre de gneiss",
    "block-loosestones-schist-free": "Pierre de schiste",
    "block-loosestones-migmatite-free": "Pierre de migmatite",
    "block-loosestones-amphibolite-free": "Pierre d'amphibolite",
    "block-loosestones-pumice-free": "Pierre de pumice",
    "block-loosestones-diorite-free": "Pierre de diorite",
    "block-loosestones-gabbro-free": "Pierre de gabbro",
    "block-loosestones-mudstone-free": "Pierre de argilite",
    "block-loosestones-jade-free": "Pierre de jade",
    "block-loosestones-jasper-free": "Pierre de jaspe",

    "block-sand-rhyolite": "Sable de rhyolite",
    "block-sand-dolostone": "Sable de dolostone",
    "block-sand-siltstone": "Sable de siltite",
    "block-sand-quartzite": "Sable de quartzite",
    "block-sand-gneiss": "Sable de gneiss",
    "block-sand-schist": "Sable de schiste",
    "block-sand-migmatite": "Sable de migmatite",
    "block-sand-amphibolite": "Sable d'amphibolite",
    "block-sand-pumice": "Sable de pumice",
    "block-sand-diorite": "Sable de diorite",
    "block-sand-gabbro": "Sable de gabbro",
    "block-sand-mudstone": "Sable de argilite",
    "block-sand-jade": "Sable de jade",
    "block-sand-jasper": "Sable de jaspe",

    "block-gravel-rhyolite": "Gravier de rhyolite",
    "block-gravel-dolostone": "Gravier de dolostone",
    "block-gravel-siltstone": "Gravier de siltite",
    "block-gravel-quartzite": "Gravier de quartzite",
    "block-gravel-gneiss": "Gravier de gneiss",
    "block-gravel-schist": "Gravier de schiste",
    "block-gravel-migmatite": "Gravier de migmatite",
    "block-gravel-amphibolite": "Gravier d'amphibolite",
    "block-gravel-pumice": "Gravier de pumice",
    "block-gravel-diorite": "Gravier de diorite",
    "block-gravel-gabbro": "Gravier de gabbro",
    "block-gravel-mudstone": "Gravier de argilite",
    "block-gravel-jade": "Gravier de jade",
    "block-gravel-jasper": "Gravier de jaspe",

    "game:block-gravel-rhyolite-land-*": "Gravier de rhyolite",
    "game:block-gravel-dolostone-land-*": "Gravier de dolostone",
    "game:block-gravel-siltstone-land-*": "Gravier de siltite",
    "game:block-gravel-quartzite-land-*": "Gravier de quartzite",
    "game:block-gravel-gneiss-land-*": "Gravier de gneiss",
    "game:block-gravel-schist-land-*": "Gravier de schiste",
    "game:block-gravel-migmatite-land-*": "Gravier de migmatite",
    "game:block-gravel-pumice-land-*": "Gravier de pumice",
    "game:block-gravel-diorite-land-*": "Gravier de diorite",
    "game:block-gravel-gabbro-land-*": "Gravier de gabbro",
    "game:block-gravel-mudstone-land-*": "Gravier de argilite",
    "game:block-gravel-amphibolite-land-*": "Gravier d'amphibolite",
    "game:block-gravel-jade-land-*": "Gravier de jade",
    "game:block-gravel-jasper-land-*": "Gravier de jaspe",

    "game:block-agedstonebricks-rhyolite": "Briques de rhyolite vieillies",
    "game:block-agedstonebricks-dolostone": "Briques de dolostone vieillies",
    "game:block-agedstonebricks-siltstone": "Briques de siltite vieillies",
    "game:block-agedstonebricks-quartzite": "Briques de quartzite vieillies",
    "game:block-agedstonebricks-gneiss": "Briques de gneiss vieillies",
    "game:block-agedstonebricks-schist": "Briques de schiste vieillies",
    "game:block-agedstonebricks-migmatite": "Briques de migmatite vieillies",
    "game:block-agedstonebricks-amphibolite": "Briques d'amphibolite vieillies",
    "game:block-agedstonebricks-pumice": "Briques de pumice vieillies",
    "game:block-agedstonebricks-diorite": "Briques de diorite vieillies",
    "game:block-agedstonebricks-gabbro": "Briques de gabbro vieillies",
    "game:block-agedstonebricks-mudstone": "Briques de argilite vieillies",
    "game:block-agedstonebricks-jade": "Briques de jade vieillies",
    "game:block-agedstonebricks-jasper": "Briques de jaspe vieillies",

    "item-stonebrick-rhyolite": "Bloc de rhyolite en pierre",
    "item-stonebrick-dolostone": "Bloc de dolostone en pierre",
    "item-stonebrick-siltstone": "Bloc de siltite en pierre",
    "item-stonebrick-quartzite": "Bloc de quartzite en pierre",
    "item-stonebrick-gneiss": "Bloc de gneiss en pierre",
    "item-stonebrick-schist": "Bloc de schiste en pierre",
    "item-stonebrick-migmatite": "Bloc de migmatite en pierre",
    "item-stonebrick-amphibolite": "Bloc d'amphibolite en pierre",
    "item-stonebrick-pumice": "Bloc de pumice en pierre",
    "item-stonebrick-diorite": "Bloc de diorite en pierre",
    "item-stonebrick-gabbro": "Bloc de gabbro en pierre",
    "item-stonebrick-mudstone": "Bloc de argilite en pierre",
    "item-stonebrick-jade": "Bloc de jade en pierre",
    "item-stonebrick-jasper": "Bloc de jaspe en pierre",

    "item-stonebrick-rhyolite": "Bloc de rhyolite",
    "item-stonebrick-dolostone": "Bloc de dolostone",
    "item-stonebrick-siltstone": "Bloc de siltite",
    "item-stonebrick-quartzite": "Bloc de quartzite",
    "item-stonebrick-gneiss": "Bloc de gneiss",
    "item-stonebrick-schist": "Bloc de schiste",
    "item-stonebrick-migmatite": "Bloc de migmatite",
    "item-stonebrick-amphibolite": "Bloc d'amphibolite",
    "item-stonebrick-pumice": "Bloc de pumice",
    "item-stonebrick-diorite": "Bloc de diorite",
    "item-stonebrick-gabbro": "Bloc de gabbro",
    "item-stonebrick-mudstone": "Bloc de argilite",
    "item-stonebrick-jade": "Bloc de jade",
    "item-stonebrick-jasper": "Bloc de jaspe", 

    "rock-rhyolite": "Rhyolite",
    "rock-dolostone": "Dolostone",
    "rock-siltstone": "Siltstone",
    "rock-quartzite": "Quartzite",
    "rock-gneiss": "Gneiss",
    "rock-schist": "Schiste",
    "rock-migmatite": "Migmatite",
    "rock-amphibolite": "Amphibolite",
    "rock-pumice": "Pumice",
    "rock-diorite": "Diorite",
    "rock-gabbro": "Gabbro",
    "rock-mudstone": "Mudstone",
    "rock-jade": "Jade",
    "rock-jasper": "Jaspe",

    "item-axehead-diorite": "Tête de hache en diorite",
    "item-hoehead-diorite": "Tête de houe en diorite",
    "item-knifeblade-diorite": "Lame de couteau en diorite",
    "item-shovelhead-diorite": "Tête de pelle en diorite",
    "item-spearhead-diorite": "Pointe de lance en diorite",
    "item-axehead-gabbro": "Tête de hache en gabbro",
    "item-hoehead-gabbro": "Tête de houe en gabbro",
    "item-knifeblade-gabbro": "Lame de couteau en gabbro",
    "item-shovelhead-gabbro": "Tête de pelle en gabbro",
    "item-spearhead-gabbro": "Pointe de lance en gabbro",
    "item-axehead-quartzite": "Tête de hache en quartzite",
    "item-hoehead-quartzite": "Tête de houe en quartzite",
    "item-knifeblade-quartzite": "Lame de couteau en quartzite",
    "item-shovelhead-quartzite": "Tête de pelle en quartzite",
    "item-spearhead-quartzite": "Pointe de lance en quartzite", 

    "item-axe-gabbro": "Hache en gabbro",
    "item-shovel-gabbro": "Pelle en gabbro",
    "item-hoe-gabbro": "Houes en gabbro",
    "item-spear-generic-gabbro": "Lance en gabbro",
    "item-knife-generic-gabbro": "Couteau en gabbro",
    "item-knife-generic-bonegabbro": "Couteau en gabbro",
    "item-axe-quartzite": "Hache en quartzite",
    "item-shovel-quartzite": "Pelle en quartzite",
    "item-hoe-quartzite": "Houes en quartzite",
    "item-spear-generic-quartzite": "Lance en quartzite",
    "item-knife-generic-quartzite": "Couteau en quartzite",
    "item-knife-generic-bonequartzite": "Couteau en quartzite",
    "item-axe-diorite": "Hache en diorite",
    "item-shovel-diorite": "Pelle en diorite",
    "item-hoe-diorite": "Houes en diorite",
    "item-spear-generic-diorite": "Lance en diorite",
    "item-knife-generic-diorite": "Couteau en diorite",
    "item-knife-generic-bonediorite": "Couteau en diorite", 

    "game:block-ore-flint-rhyolite": "Silex dans la rhyolite",
    "game:block-ore-flint-dolostone": "Silex dans le dolostone",
    "game:block-ore-flint-siltstone": "Silex dans le siltite",
    "game:block-ore-flint-quartzite": "Silex dans le quartzite",
    "game:block-ore-flint-gneiss": "Silex dans le gneiss",
    "game:block-ore-flint-schist": "Silex dans le schiste",
    "game:block-ore-flint-migmatite": "Silex dans la migmatite",
    "game:block-ore-flint-amphibolite": "Silex dans l'amphibolite",
    "game:block-ore-flint-pumice": "Silex dans la pumice",
    "game:block-ore-flint-diorite": "Silex dans la diorite",
    "game:block-ore-flint-gabbro": "Silex dans le gabbro",
    "game:block-ore-flint-mudstone": "Silex dans le argilite",
    "game:block-ore-flint-jade": "Silex dans le jade",
    "game:block-ore-flint-jasper": "Silex dans le jaspe",
        
    "game:block-looseores-azurite-*": "Morceaux de minerai de cuivre",
    "game:block-looseores-pyrite-*": "Morceaux de minerai de pyrite",
    "game:block-looseores-chalcopyrite-*": "Morceaux de minerai de chalcopyrite",
    "game:block-looseores-vanadinite-*": "Morceaux de minerai de vanadinite",
    "game:block-looseores-wulfenite-*": "Morceaux de minerai de wulfenite",
    "game:block-looseores-teallite-*": "Morceaux de minerai de teallite",
    "game:block-looseores-franckeite-*": "Morceaux de minerai de franckeite",
    "game:block-looseores-cerussite-*": "Morceaux de minerai de cérusite",
    "game:block-looseores-chalcocite-*": "Morceaux de minerai de chalcocite",
    "game:block-looseores-freibergite-*": "Morceaux de minerai de freibergite",
    "game:block-looseores-hemimorphite-*": "Morceaux de minerai de hémimorphite",
    "game:block-looseores-smithsonite-*": "Morceaux de minerai de smithsonite",
    "game:block-looseores-tetrahedrite-*": "Morceaux de minerai de tétraédrite",
    "game:block-looseores-sperrylite-*": "Morceaux de minerai de sperrylite",
    "game:block-looseores-nativeplatinum-*": "Morceaux de minerai de platine natif", 

    "game:ore-azurite": "Azurite",
    "game:ore-pyrite": "Pyrite",
    "game:ore-chalcopyrite": "Chalcopyrite",
    "game:ore-vanadinite": "Vanadinite",
    "game:ore-wulfenite": "Wulfénite",
    "game:ore-teallite": "Théallite",
    "game:ore-franckeite": "Franckéite",
    "game:ore-cerussite": "Cérusite",
    "game:ore-chalcocite": "Chalcocite",
    "game:ore-freibergite": "Freibergite",
    "game:ore-hemimorphite": "Hémimorphite",
    "game:ore-smithsonite": "Smithsonite",
    "game:ore-tetrahedrite": "Tétraédrite",
    "game:ore-sperrylite": "Sperrylite",
    "game:ore-nativeplatinum": "Platine natif",
    "game:item-stone-bogiron": "Fer des marais", 

    "game:block-ore-*-azurite-*": "Minerai d'azurite",
    "game:block-ore-*-pyrite-*": "Minerai de pyrite",
    "game:block-ore-*-chalcopyrite-*": "Minerai de chalcopyrite",
    "game:block-ore-*-vanadinite-*": "Minerai de vanadinite",
    "game:block-ore-*-wulfenite-*": "Minerai de wulfénite",
    "game:block-ore-*-teallite-*": "Minerai de théallite",
    "game:block-ore-*-franckeite-*": "Minerai de franckéite",
    "game:block-ore-*-cerussite-*": "Minerai de cérusite",
    "game:block-ore-*-chalcocite-*": "Minerai de chalcocite",
    "game:block-ore-*-freibergite-*": "Minerai de freibergite",
    "game:block-ore-*-hemimorphite-*": "Minerai d'hémimorphite",
    "game:block-ore-*-smithsonite-*": "Minerai de smithsonite",
    "game:block-ore-*-tetrahedrite-*": "Minerai de tétraédrite",
    "game:block-ore-*-sperrylite-*": "Minerai de sperrylite",
    "game:block-ore-*-nativeplatinum-*": "Minerai de platine natif",
    "game:block-bogiron": "Minerai de fer des marais", 

    "game:item-nugget-azurite": "Pépite (Azurite)",
    "game:item-nugget-pyrite": "Pépite (Pyrite)",
    "game:item-nugget-chalcopyrite": "Pépite (Chalcopyrite)",
    "game:item-nugget-vanadinite": "Pépite (Vanadinite)",
    "game:item-nugget-wulfenite": "Pépite (Wulfénite)",
    "game:item-nugget-teallite": "Pépite (Théallite)",
    "game:item-nugget-franckeite": "Pépite (Franckeite)",
    "game:item-nugget-cerussite": "Pépite (Cérusite)",
    "game:item-nugget-chalcocite": "Pépite (Chalcocite)",
    "game:item-nugget-freibergite": "Pépite (Freibergite)",
    "game:item-nugget-hemimorphite": "Pépite (Hémimorphite)",
    "game:item-nugget-smithsonite": "Pépite (Smithsonite)",
    "game:item-nugget-tetrahedrite": "Pépite (Tétraédrite)",
    "game:item-nugget-sperrylite": "Pépite (Sperrylite)",
    "game:item-nugget-nativeplatinum": "Pépite (Platine natif)",

    "game:block-looseores-corundumruby-*": "Morceaux de Rubis",
    "game:block-ore-low-corundumruby-*": "Rubis (de faible qualité)",
    "game:block-ore-medium-corundumruby-*": "Rubis (de qualité moyenne)",
    "game:block-ore-high-corundumruby-*": "Rubis (de haute qualité)",
    "game:item-gem-corundumruby-rough": "Rubis brut",
    "game:ore-corundumruby": "Rubis",

    "game:block-looseores-corundumsapphire-*": "Morceaux de Saphir",
    "game:block-ore-low-corundumsapphire-*": "Saphir (de faible qualité)",
    "game:block-ore-medium-corundumsapphire-*": "Saphir (de qualité moyenne)",
    "game:block-ore-high-corundumsapphire-*": "Saphir (de haute qualité)",
    "game:item-gem-corundumsapphire-rough": "Saphir brut",
    "game:ore-corundumsapphire": "Saphir",

    "game:block-looseores-topazamber-*": "Morceaux de Topaze Ambre",
    "game:block-ore-low-topazamber-*": "Topaze Ambre (de faible qualité)",
    "game:block-ore-medium-topazamber-*": "Topaze Ambre (de qualité moyenne)",
    "game:block-ore-high-topazamber-*": "Topaze Ambre (de haute qualité)",
    "game:item-gem-topazamber-rough": "Topaze Ambre brute",
    "game:ore-topazamber": "Topaze Ambre",

    "game:block-looseores-topazblue-*": "Morceaux de Topaze Bleue",
    "game:block-ore-low-topazblue-*": "Topaze Bleue (de faible qualité)",
    "game:block-ore-medium-topazblue-*": "Topaze Bleue (de qualité moyenne)",
    "game:block-ore-high-topazblue-*": "Topaze Bleue (de haute qualité)",
    "game:item-gem-topazblue-rough": "Topaze Bleue brute",
    "game:ore-topazblue": "Topaze Bleue",

    "game:block-looseores-topazpink-*": "Morceaux de Topaze Rose",
    "game:block-ore-low-topazpink-*": "Topaze Rose (de faible qualité)",
    "game:block-ore-medium-topazpink-*": "Topaze Rose (de qualité moyenne)",
    "game:block-ore-high-topazpink-*": "Topaze Rose (de haute qualité)",
    "game:item-gem-topazpink-rough": "Topaze Rose brute",
    "game:ore-topazpink": "Topaze Rose",

    "game:block-looseores-spinelred-*": "Morceaux de Spinelle",
    "game:block-ore-low-spinelred-*": "Spinelle (de faible qualité)",
    "game:block-ore-medium-spinelred-*": "Spinelle (de qualité moyenne)",
    "game:block-ore-high-spinelred-*": "Spinelle (de haute qualité)",
    "game:item-gem-spinelred-rough": "Spinelle brute",
    "game:ore-spinelred": "Spinelle",

    "game:block-looseores-berylaquamarine-*": "Morceaux d'Aigue-marine",
    "game:block-ore-low-berylaquamarine-*": "Aigue-marine (de faible qualité)",
    "game:block-ore-medium-berylaquamarine-*": "Aigue-marine (de qualité moyenne)",
    "game:block-ore-high-berylaquamarine-*": "Aigue-marine (de haute qualité)",
    "game:item-gem-berylaquamarine-rough": "Aigue-marine brute",
    "game:ore-berylaquamarine": "Aigue-marine",

    "game:block-looseores-berylbixbite-*": "Morceaux de Bixbite",
    "game:block-ore-low-berylbixbite-*": "Bixbite (de faible qualité)",
    "game:block-ore-medium-berylbixbite-*": "Bixbite (de qualité moyenne)",
    "game:block-ore-high-berylbixbite-*": "Bixbite (de haute qualité)",
    "game:item-gem-berylbixbite-rough": "Bixbite brut",
    "game:ore-berylbixbite": "Bixbite",

    "game:block-looseores-garnetspessartine-*": "Morceaux de Grenat Spessartine",
    "game:block-ore-low-garnetspessartine-*": "Grenat Spessartine (de faible qualité)",
    "game:block-ore-medium-garnetspessartine-*": "Grenat Spessartine (de qualité moyenne)",
    "game:block-ore-high-garnetspessartine-*": "Grenat Spessartine (de haute qualité)",
    "game:item-gem-garnetspessartine-rough": "Grenat Spessartine brut",
    "game:ore-garnetspessartine": "Grenat Spessartine",

    "game:block-looseores-garnetuvarovite-*": "Morceaux de Grenat Uvarovite",
    "game:block-ore-low-garnetuvarovite-*": "Grenat Uvarovite (de faible qualité)",
    "game:block-ore-medium-garnetuvarovite-*": "Grenat Uvarovite (de qualité moyenne)",
    "game:block-ore-high-garnetuvarovite-*": "Grenat Uvarovite (de haute qualité)",
    "game:item-gem-garnetuvarovite-rough": "Grenat Uvarovite brut",
    "game:ore-garnetuvarovite": "Grenat Uvarovite",

    "game:block-looseores-garnetalmandine-*": "Morceaux de Grenat Almandine",
    "game:block-ore-low-garnetalmandine-*": "Grenat Almandine (de faible qualité)",
    "game:block-ore-medium-garnetalmandine-*": "Grenat Almandine (de qualité moyenne)",
    "game:block-ore-high-garnetalmandine-*": "Grenat Almandine (de haute qualité)",
    "game:item-gem-garnetalmandine-rough": "Grenat Almandine brut",
    "game:ore-garnetalmandine": "Grenat Almandine",

    "game:block-looseores-garnetpyrope-*": "Morceaux de Grenat Pyrope",
    "game:block-ore-low-garnetpyrope-*": "Grenat Pyrope (de faible qualité)",
    "game:block-ore-medium-garnetpyrope-*": "Grenat Pyrope (de qualité moyenne)",
    "game:block-ore-high-garnetpyrope-*": "Grenat Pyrope (de haute qualité)",
    "game:item-gem-garnetpyrope-rough": "Grenat Pyrope brut",
    "game:ore-garnetpyrope": "Grenat Pyrope",

    "game:block-looseores-garnetgrossular-*": "Morceaux de Grenat Grossulaire",
    "game:block-ore-low-garnetgrossular-*": "Grenat Grossulaire (de faible qualité)",
    "game:block-ore-medium-garnetgrossular-*": "Grenat Grossulaire (de qualité moyenne)",
    "game:block-ore-high-garnetgrossular-*": "Grenat Grossulaire (de haute qualité)",
    "game:item-gem-garnetgrossular-rough": "Grenat Grossulaire brut",
    "game:ore-garnetgrossular": "Grenat Grossulaire",

    "game:block-looseores-garnetandradite-*": "Morceaux de Grenat Andradite",
    "game:block-ore-low-garnetandradite-*": "Grenat Andradite (de faible qualité)",
    "game:block-ore-medium-garnetandradite-*": "Grenat Andradite (de qualité moyenne)",
    "game:block-ore-high-garnetandradite-*": "Grenat Andradite (de haute qualité)",
    "game:item-gem-garnetandradite-rough": "Grenat Andradite brut",
    "game:ore-garnetandradite": "Grenat Andradite",

    "game:block-looseores-tourmalineschorl-*": "Morceaux de Tourmaline Schorl",
    "game:block-ore-low-tourmalineschorl-*": "Tourmaline Schorl (de faible qualité)",
    "game:block-ore-medium-tourmalineschorl-*": "Tourmaline Schorl (de qualité moyenne)",
    "game:block-ore-high-tourmalineschorl-*": "Tourmaline Schorl (de haute qualité)",
    "game:item-gem-tourmalineschorl-rough": "Tourmaline Schorl brute",
    "game:ore-tourmalineschorl": "Tourmaline Schorl",

    "game:block-looseores-tourmalineverdelite-*": "Morceaux de Tourmaline Verdelite",
    "game:block-ore-low-tourmalineverdelite-*": "Tourmaline Verdelite (qualité inférieure)",
    "game:block-ore-medium-tourmalineverdelite-*": "Tourmaline Verdelite (qualité moyenne)",
    "game:block-ore-high-tourmalineverdelite-*": "Tourmaline Verdelite (haute qualité)",
    "game:item-gem-tourmalineverdelite-rough": "Tourmaline Verdelite brute",
    "game:ore-tourmalineverdelite": "Tourmaline Verdelite",

    "game:block-looseores-tourmalinerubellite-*": "Morceaux de Tourmaline Rubellite",
    "game:block-ore-low-tourmalinerubellite-*": "Tourmaline Rubellite (qualité inférieure)",
    "game:block-ore-medium-tourmalinerubellite-*": "Tourmaline Rubellite (qualité moyenne)",
    "game:block-ore-high-tourmalinerubellite-*": "Tourmaline Rubellite (haute qualité)",
    "game:item-gem-tourmalinerubellite-rough": "Tourmaline Rubellite brute",
    "game:ore-tourmalinerubellite": "Tourmaline Rubellite",

    "game:block-looseores-tourmalinewatermelon-*": "Morceaux de Tourmaline Pastèque",
    "game:block-ore-low-tourmalinewatermelon-*": "Tourmaline Pastèque (qualité inférieure)",
    "game:block-ore-medium-tourmalinewatermelon-*": "Tourmaline Pastèque (qualité moyenne)",
    "game:block-ore-high-tourmalinewatermelon-*": "Tourmaline Pastèque (haute qualité)",
    "game:item-gem-tourmalinewatermelon-rough": "Tourmaline Pastèque brute",
    "game:ore-tourmalinewatermelon": "Tourmaline Pastèque",

    "game:block-sodastraws-*": "Paille de Soda",

    "block-crystal-citrine-small1-up": "Petit cristal de citrine (variante 1)",

    "block-crystal-citrine-small2-up": "Petit cristal de citrine (variante 2)",

    "block-crystal-citrine-small3-up": "Petit cristal de citrine (variante 3)",

    "block-crystal-citrine-large1-up": "Grand cristal de citrine (variante 1)",

    "block-crystal-citrine-large2-up": "Grand cristal de citrine (variante 2)",

    "block-crystal-citrine-cluster1-up": "Groupe de citrine (variante 1)",

    "block-crystal-citrine-cluster2-up": "Groupe de citrine (variante 2)",
    "item-citrine": "Citrine",

    "item-handbooktitle-citrine": "Comment fabriquer du verre :",

    "item-handbooktext-citrine": "<a href=\"handbook://craftinginfo-smelting\">La Fusion</a> de la citrine nécessite des températures trop élevées pour les combustibles ordinaires. Utilisez un <a href=\"handbook://block-bloomerybase-north\">four à chaux</a> pour fondre la citrine en verre.",
    
    "game:block-polishedrockold-full-gabbro": "Pierre polie vieillie (Gabbro)",
    "game:block-polishedrockold-full-amphibolite": "Pierre polie vieillie (Amphibolite)",
    "game:block-polishedrockold-full-gneiss": "Pierre polie vieillie (Gneiss)",
    "game:block-polishedrockold-full-migmatite": "Pierre polie vieillie (Migmatite)",
    "game:block-polishedrockold-full-schist": "Pierre polie vieillie (Schiste)",
    "game:block-polishedrockold-full-mudstone": "Pierre polie vieillie (Mudstone)",
    "game:block-polishedrockold-full-diorite": "Pierre polie vieillie (Diorite)",
    "game:block-polishedrockold-full-siltstone": "Pierre polie vieillie (Siltstone)",
    "game:block-polishedrockold-full-dolostone": "Pierre polie vieillie (Dolostone)",
    "game:block-polishedrockold-full-rhyolite": "Pierre polie vieillie (Rhyolite)",
    "game:block-polishedrockold-full-quartzite": "Pierre polie vieillie (Quartzite)",
    "game:block-polishedrockold-full-pumice": "Pierre polie vieillie (Pumice)",
    "game:block-polishedrockold-full-jasper": "Pierre polie vieillie (Jasper)",
    "game:block-polishedrockold-full-jade": "Pierre polie vieillie (Jade)",

    "game:block-polishedrockold-cobbled-gabbro": "Pierre polie pavée vieillie (Gabbro)",
    "game:block-polishedrockold-cobbled-amphibolite": "Pierre polie pavée vieillie (Amphibolite)",
    "game:block-polishedrockold-cobbled-gneiss": "Pierre polie pavée vieillie (Gneiss)",
    "game:block-polishedrockold-cobbled-migmatite": "Pierre polie pavée vieillie (Migmatite)",
    "game:block-polishedrockold-cobbled-schist": "Pierre polie pavée vieillie (Schiste)",
    "game:block-polishedrockold-cobbled-mudstone": "Pierre polie pavée vieillie (Mudstone)",
    "game:block-polishedrockold-cobbled-diorite": "Pierre polie pavée vieillie (Diorite)",
    "game:block-polishedrockold-cobbled-siltstone": "Pierre polie pavée vieillie (Siltstone)",
    "game:block-polishedrockold-cobbled-dolostone": "Pierre polie pavée vieillie (Dolostone)",
    "game:block-polishedrockold-cobbled-rhyolite": "Pierre polie pavée vieillie (Rhyolite)",
    "game:block-polishedrockold-cobbled-quartzite": "Pierre polie pavée vieillie (Quartzite)",
    "game:block-polishedrockold-cobbled-pumice": "Pierre polie pavée vieillie (Pumice)",
    "game:block-polishedrockold-cobbled-jasper": "Pierre polie pavée vieillie (Jasper)",
    "game:block-polishedrockold-cobbled-jade": "Pierre polie pavée vieillie (Jade)",

    "block-crackedstonebricks-rhyolite": "Briques de rhyolite fissurées",
    "block-crackedstonebricks-dolostone": "Briques de dolostone fissurées",
    "block-crackedstonebricks-siltstone": "Briques de siltite fissurées",
    "block-crackedstonebricks-quartzite": "Briques de quartzite fissurées",
    "block-crackedstonebricks-gneiss": "Briques de gneiss fissurées",
    "block-crackedstonebricks-schist": "Briques de schiste fissurées",
    "block-crackedstonebricks-migmatite": "Briques de migmatite fissurées",
    "block-crackedstonebricks-amphibolite": "Briques d'amphibolite fissurées",
    "block-crackedstonebricks-pumice": "Briques de pumice fissurées",
    "block-crackedstonebricks-diorite": "Briques de diorite fissurées",
    "block-crackedstonebricks-gabbro": "Briques de gabbro fissurées",
    "block-crackedstonebricks-mudstone": "Briques de argilite fissurées",
    "block-crackedstonebricks-jasper": "Briques de jasper fissurées",
    "block-crackedstonebricks-jade": "Briques de jade fissurées",

    "item-snowball-rhyolite": "Pierre de rhyolite dans une boule de neige",
    "item-snowball-dolostone": "Pierre de dolostone dans une boule de neige",
    "item-snowball-siltstone": "Pierre de siltite dans une boule de neige",
    "item-snowball-quartzite": "Pierre de quartzite dans une boule de neige",
    "item-snowball-gneiss": "Pierre de gneiss dans une boule de neige",
    "item-snowball-schist": "Pierre de schiste dans une boule de neige",
    "item-snowball-migmatite": "Pierre de migmatite dans une boule de neige",
    "item-snowball-amphibolite": "Pierre d'amphibolite dans une boule de neige",
    "item-snowball-pumice": "Pierre de pumice dans une boule de neige",
    "item-snowball-diorite": "Pierre de diorite dans une boule de neige",
    "item-snowball-gabbro": "Pierre de gabbro dans une boule de neige",
    "item-snowball-mudstone": "Pierre de argilite dans une boule de neige",
    "item-snowball-jasper": "Pierre de jasper dans une boule de neige",
    "item-snowball-jade": "Pierre de jade dans une boule de neige",
    "item-snowball-bogiron": "Boule de neige rouillée",

    "item-axe-bone-diorite": "Hache en diorite",
    "item-axe-bone-gabbro": "Hache en gabbro",
    "item-axe-bone-quartzite": "Hache en quartzite",

    "block-quern-diorite": "Meule en diorite",
    "block-quern-gabbro": "Meule en gabbro",
    "block-quern-rhyolite": "Meule en rhyolite"

}
